[
    {
        "rank": "1",
        "title": "용애담",
        "artist": "채채, 요요",
        "imageURL": "https://ccdn.lezhin.com/v2/comics/6635899332132864/images/tall.webp?updated=1709025894954&width=156 2x",
        "category": "BL"
    },
    {
        "rank": "2",
        "title": "용애담",
        "artist": "들개이빨",
        "imageURL": "https://ccdn.lezhin.com/v2/comics/119/images/tall.webp?updated=1655863645420&width=156 2x",
        "category": "일상"
    },
    {
        "rank": "3",
        "title": "용애담",
        "artist": "개구락지",
        "imageURL": "https://ccdn.lezhin.com/v2/comics/4842032246620160/images/tall.webp?updated=1693802419903&width=156 2x",
        "category": "학원"
    },
    {
        "rank": "4",
        "title": "용애담",
        "artist": "박지",
        "imageURL": "https://ccdn.lezhin.com/v2/comics/5082862571421696/images/tall.webp?updated=1704526550716&width=156 2x",
        "category": "학원"
    },
    {
        "rank": "5",
        "title": "용애담",
        "artist": "고지라군",
        "imageURL": "https://ccdn.lezhin.com/v2/comics/248/images/tall.webp?updated=1649059443521&width=156 2x",
        "category": "판타지"
    },
    {
        "rank": "6",
        "title": "용애담",
        "artist": "M, 유인, 마카로니, 초운, 차한나",
        "imageURL": "https://ccdn.lezhin.com/v2/comics/6163779083763712/images/tall.webp?updated=1706861549935&width=156 2x",
        "category": "로맨스"
    },
    {
        "rank": "7",
        "title": "용애담",
        "artist": "엉덩국",
        "imageURL": "https://ccdn.lezhin.com/v2/comics/5794272204095488/images/tall.webp?updated=1670209061360&width=156 2x",
        "category": "개그"
    },
    {
        "rank": "8",
        "title": "용애담",
        "artist": "jierana, HanY, hakire_chui, COL GROUP&FTL Culture",
        "imageURL": "https://ccdn.lezhin.com/v2/comics/6342206661263360/images/tall.webp?updated=1709017804388&width=156 2x",
        "category": "로맨스"
    },
    {
        "rank": "9",
        "title": "용애담",
        "artist": "레바",
        "imageURL": null,
        "category": "일상"
    },
    {
        "rank": "10",
        "title": "용애담",
        "artist": "하우진",
        "imageURL": null,
        "category": "학원"
    },
    {
        "rank": "11",
        "title": "용애담",
        "artist": "마루코믹스, 슈룹",
        "imageURL": null,
        "category": "로맨스"
    },
    {
        "rank": "12",
        "title": "용애담",
        "artist": "DIAN, 샌도, 솔체",
        "imageURL": null,
        "category": "로맨스"
    },
    {
        "rank": "13",
        "title": "용애담",
        "artist": "슬라정",
        "imageURL": "https://ccdn.lezhin.com/v2/comics/6727405857669120/images/tall.webp?updated=1712112801310&width=156 2x",
        "category": "개그"
    },
    {
        "rank": "14",
        "title": "용애담",
        "artist": "비온후",
        "imageURL": "https://ccdn.lezhin.com/v2/comics/4526490060128256/images/tall.webp?updated=1695295943568&width=156 2x",
        "category": "로맨스"
    },
    {
        "rank": "15",
        "title": "용애담",
        "artist": "볼드, 징솔",
        "imageURL": "https://ccdn.lezhin.com/v2/comics/4528546355806208/images/tall.webp?updated=1714482985811&width=156 2x",
        "category": "BL"
    },
    {
        "rank": "16",
        "title": "용애담",
        "artist": "삭둑",
        "imageURL": "https://ccdn.lezhin.com/v2/comics/6093218132590592/images/tall.webp?updated=1691058942322&width=156 2x",
        "category": "판타지"
    },
    {
        "rank": "17",
        "title": "용애담",
        "artist": "김파스",
        "imageURL": "https://ccdn.lezhin.com/v2/comics/5183802990723072/images/tall.webp?updated=1706523722569&width=156 2x",
        "category": "BL"
    },
    {
        "rank": "18",
        "title": "용애담",
        "artist": "금요정",
        "imageURL": "https://ccdn.lezhin.com/v2/comics/5376382661361664/images/tall.webp?updated=1654570205989&width=156 2x",
        "category": "개그"
    },
    {
        "rank": "19",
        "title": "용애담",
        "artist": "스즈키 유토",
        "imageURL": "https://ccdn.lezhin.com/v2/comics/6249945052282880/images/tall.webp?updated=1682302253479&width=156 2x",
        "category": "액션"
    },
    {
        "rank": "20",
        "title": "용애담",
        "artist": "박바퀴",
        "imageURL": "https://ccdn.lezhin.com/v2/comics/6185833387393024/images/tall.webp?updated=1660274231631&width=156 2x",
        "category": "일상"
    },
    {
        "rank": "21",
        "title": "용애담",
        "artist": "양념갈비, 전오랑, 전은정",
        "imageURL": "https://ccdn.lezhin.com/v2/comics/5415068762963968/images/tall.webp?updated=1677468148694&width=156 2x",
        "category": "로맨스"
    },
    {
        "rank": "22",
        "title": "용애담",
        "artist": "핑푸",
        "imageURL": "https://ccdn.lezhin.com/v2/comics/59/images/tall.webp?updated=1709721099701&width=156 2x",
        "category": "판타지"
    },
    {
        "rank": "23",
        "title": "용애담",
        "artist": "청연",
        "imageURL": "https://ccdn.lezhin.com/v2/comics/4952778572890112/images/tall.webp?updated=1712724126856&width=156 2x",
        "category": "BL"
    },
    {
        "rank": "24",
        "title": "용애담",
        "artist": "배드이리",
        "imageURL": "https://ccdn.lezhin.com/v2/comics/5558254478557184/images/tall.webp?updated=1625736458521&width=156 2x",
        "category": "개그"
    },
    {
        "rank": "25",
        "title": "용애담",
        "artist": "맛감쟈",
        "imageURL": "https://ccdn.lezhin.com/v2/comics/6131748064919552/images/tall.webp?updated=1707895496389&width=156 2x",
        "category": "학원"
    },
    {
        "rank": "26",
        "title": "용애담",
        "artist": "박하, 하과, 꿈결나무",
        "imageURL": "https://ccdn.lezhin.com/v2/comics/5112866230042624/images/tall.webp?updated=1697092946850&width=156 2x",
        "category": "로맨스"
    },
    {
        "rank": "27",
        "title": "용애담",
        "artist": "영일",
        "imageURL": null,
        "category": "일상"
    },
    {
        "rank": "28",
        "title": "용애담",
        "artist": "허건, 난나, 채팔이",
        "imageURL": null,
        "category": "BL"
    },
    {
        "rank": "29",
        "title": "용애담",
        "artist": "한세람, 톰",
        "imageURL": "https://ccdn.lezhin.com/v2/comics/4562605903773696/images/tall.webp?updated=1645503183947&width=156 2x",
        "category": "로맨스"
    },
    {
        "rank": "30",
        "title": "용애담",
        "artist": "임서림, 이영유",
        "imageURL": "https://ccdn.lezhin.com/v2/comics/4866953452781568/images/tall.webp?updated=1701409672855&width=156 2x",
        "category": "로맨스"
    },
    {
        "rank": "31",
        "title": "용애담",
        "artist": "문토, 윤달(YounDal)",
        "imageURL": "https://ccdn.lezhin.com/v2/comics/4682720685654016/images/tall.webp?updated=1683869554794&width=156 2x",
        "category": "로맨스"
    },
    {
        "rank": "32",
        "title": "용애담",
        "artist": "청건",
        "imageURL": "https://ccdn.lezhin.com/v2/comics/6301365414658048/images/tall.webp?updated=1602323500283&width=156 2x",
        "category": "학원"
    },
    {
        "rank": "33",
        "title": "용애담",
        "artist": "천호냥",
        "imageURL": "https://ccdn.lezhin.com/v2/comics/5547609250136064/images/tall.webp?updated=1691113243965&width=156 2x",
        "category": "학원"
    },
    {
        "rank": "34",
        "title": "용애담",
        "artist": "꽉",
        "imageURL": "https://ccdn.lezhin.com/v2/comics/6005406548426752/images/tall.webp?updated=1713686422826&width=156 2x",
        "category": "판타지"
    },
    {
        "rank": "35",
        "title": "용애담",
        "artist": "차현",
        "imageURL": "https://ccdn.lezhin.com/v2/comics/6234227991969792/images/tall.webp?updated=1704768248000&width=156 2x",
        "category": "BL"
    },
    {
        "rank": "36",
        "title": "용애담",
        "artist": "썸머",
        "imageURL": "https://ccdn.lezhin.com/v2/comics/5582295969628160/images/tall.webp?updated=1710845275288&width=156 2x",
        "category": "BL"
    },
    {
        "rank": "37",
        "title": "용애담",
        "artist": "퍄퍄",
        "imageURL": "https://ccdn.lezhin.com/v2/comics/5436405380743168/images/tall.webp?updated=1714481202107&width=156 2x",
        "category": "로맨스"
    },
    {
        "rank": "38",
        "title": "용애담",
        "artist": "ANGELA, 비작, 허니트랩",
        "imageURL": "https://ccdn.lezhin.com/v2/comics/6313950063689728/images/tall.webp?updated=1692693039892&width=156 2x",
        "category": "BL"
    },
    {
        "rank": "39",
        "title": "용애담",
        "artist": "야무라 이치",
        "imageURL": "https://ccdn.lezhin.com/v2/comics/5256115748929536/images/tall.webp?updated=1697179054252&width=156 2x",
        "category": "백합"
    },
    {
        "rank": "40",
        "title": "용애담",
        "artist": "카네다 요스케",
        "imageURL": "https://ccdn.lezhin.com/v2/comics/6362472089255936/images/tall.webp?updated=1613370272582&width=156 2x",
        "category": "로맨스"
    },
    {
        "rank": "41",
        "title": "용애담",
        "artist": "와카마츠 타카히로, 노다 히로시",
        "imageURL": "https://ccdn.lezhin.com/v2/comics/6276822873735168/images/tall.webp?updated=1710117340830&width=156 2x",
        "category": "로맨스"
    },
    {
        "rank": "42",
        "title": "용애담",
        "artist": "깜지루",
        "imageURL": "https://ccdn.lezhin.com/v2/comics/5758960471965696/images/tall.webp?updated=1690957311375&width=156 2x",
        "category": "일상"
    },
    {
        "rank": "43",
        "title": "용애담",
        "artist": "하리보",
        "imageURL": null,
        "category": "BL"
    },
    {
        "rank": "44",
        "title": "용애담",
        "artist": "백리군혜, 강당",
        "imageURL": null,
        "category": "BL"
    },
    {
        "rank": "45",
        "title": "용애담",
        "artist": "환댕",
        "imageURL": "https://ccdn.lezhin.com/v2/comics/6217220923850752/images/tall.webp?updated=1698300510403&width=156 2x",
        "category": "판타지"
    },
    {
        "rank": "46",
        "title": "용애담",
        "artist": "허긴개",
        "imageURL": "https://ccdn.lezhin.com/v2/comics/5308438415671296/images/tall.webp?updated=1687507103279&width=156 2x",
        "category": "액션"
    },
    {
        "rank": "47",
        "title": "용애담",
        "artist": "진돌",
        "imageURL": "https://ccdn.lezhin.com/v2/comics/6383971435413504/images/tall.webp?updated=1626417765457&width=156 2x",
        "category": "일상"
    },
    {
        "rank": "48",
        "title": "용애담",
        "artist": "NAKTA",
        "imageURL": "https://ccdn.lezhin.com/v2/comics/5015838139940864/images/tall.webp?updated=1688122918249&width=156 2x",
        "category": "학원"
    },
    {
        "rank": "49",
        "title": "용애담",
        "artist": "무선혜드셋, 빠타",
        "imageURL": "https://ccdn.lezhin.com/v2/comics/4686578887491584/images/tall.webp?updated=1713341943680&width=156 2x",
        "category": "개그"
    },
    {
        "rank": "50",
        "title": "용애담",
        "artist": "마사토끼, 입개",
        "imageURL": "https://ccdn.lezhin.com/v2/comics/4609020734078976/images/tall.webp?updated=1565590876343&width=156 2x",
        "category": "드라마"
    },
    {
        "rank": "51",
        "title": "용애담",
        "artist": "우왕이, 핫핑크",
        "imageURL": "https://ccdn.lezhin.com/v2/comics/4948172147064832/images/tall.webp?updated=1697273681722&width=156 2x",
        "category": "판타지"
    },
    {
        "rank": "52",
        "title": "용애담",
        "artist": "노커",
        "imageURL": "https://ccdn.lezhin.com/v2/comics/235/images/tall.webp?updated=1533904309733&width=156 2x",
        "category": "판타지"
    },
    {
        "rank": "53",
        "title": "용애담",
        "artist": "하마지 아키",
        "imageURL": "https://ccdn.lezhin.com/v2/comics/5774499132538880/images/tall.webp?updated=1676974377697&width=156 2x",
        "category": "개그"
    },
    {
        "rank": "54",
        "title": "용애담",
        "artist": "벽가벽, 막묵",
        "imageURL": "https://ccdn.lezhin.com/v2/comics/4645740032360448/images/tall.webp?updated=1706249576483&width=156 2x",
        "category": "액션"
    },
    {
        "rank": "55",
        "title": "용애담",
        "artist": "귀귀",
        "imageURL": "https://ccdn.lezhin.com/v2/comics/5130280144601088/images/tall.webp?updated=1714110282688&width=156 2x",
        "category": "개그"
    },
    {
        "rank": "56",
        "title": "용애담",
        "artist": "오솟",
        "imageURL": "https://ccdn.lezhin.com/v2/comics/4733152235356160/images/tall.webp?updated=1626417540383&width=156 2x",
        "category": "개그"
    },
    {
        "rank": "57",
        "title": "용애담",
        "artist": "govy",
        "imageURL": "https://ccdn.lezhin.com/v2/comics/5132794414170112/images/tall.webp?updated=1711009690840&width=156 2x",
        "category": "판타지"
    },
    {
        "rank": "58",
        "title": "용애담",
        "artist": "양말젤리",
        "imageURL": "https://ccdn.lezhin.com/v2/comics/5596969058500608/images/tall.webp?updated=1674890816228&width=156 2x",
        "category": "개그"
    },
    {
        "rank": "59",
        "title": "용애담",
        "artist": "언젯, 단남",
        "imageURL": null,
        "category": "BL"
    },
    {
        "rank": "60",
        "title": "용애담",
        "artist": "늴릴, GMAN",
        "imageURL": null,
        "category": "판타지"
    },
    {
        "rank": "61",
        "title": "용애담",
        "artist": "뭐가요, 토마토",
        "imageURL": null,
        "category": "판타지"
    },
    {
        "rank": "62",
        "title": "용애담",
        "artist": "바싹탄숯",
        "imageURL": null,
        "category": "판타지"
    },
    {
        "rank": "63",
        "title": "용애담",
        "artist": "폴빠",
        "imageURL": "https://ccdn.lezhin.com/v2/comics/27/images/tall.webp?updated=1597740352830&width=156 2x",
        "category": "판타지"
    },
    {
        "rank": "64",
        "title": "용애담",
        "artist": "김도",
        "imageURL": "https://ccdn.lezhin.com/v2/comics/5978137257574400/images/tall.webp?updated=1626417880298&width=156 2x",
        "category": "일상"
    },
    {
        "rank": "65",
        "title": "용애담",
        "artist": "채군",
        "imageURL": "https://ccdn.lezhin.com/v2/comics/6127795410632704/images/tall.webp?updated=1688123735586&width=156 2x",
        "category": "학원"
    },
    {
        "rank": "66",
        "title": "용애담",
        "artist": "수사반장",
        "imageURL": "https://ccdn.lezhin.com/v2/comics/5551016703033344/images/tall.webp?updated=1679622992512&width=156 2x",
        "category": "드라마"
    },
    {
        "rank": "67",
        "title": "용애담",
        "artist": "건일",
        "imageURL": "https://ccdn.lezhin.com/v2/comics/5083041455472640/images/tall.webp?updated=1635507374240&width=156 2x",
        "category": "학원"
    },
    {
        "rank": "68",
        "title": "용애담",
        "artist": "타랑, 몬냥",
        "imageURL": "https://ccdn.lezhin.com/v2/comics/5854708112818176/images/tall.webp?updated=1630633739270&width=156 2x",
        "category": "백합"
    },
    {
        "rank": "69",
        "title": "용애담",
        "artist": "산작약",
        "imageURL": "https://ccdn.lezhin.com/v2/comics/4790228505591808/images/tall.webp?updated=1546570802636&width=156 2x",
        "category": "판타지"
    },
    {
        "rank": "70",
        "title": "용애담",
        "artist": "호카미 나츠키, 고토게 코요하루",
        "imageURL": "https://ccdn.lezhin.com/v2/comics/5702795253841920/images/tall.webp?updated=1712902590496&width=156 2x",
        "category": "개그"
    },
    {
        "rank": "71",
        "title": "용애담",
        "artist": "크로옹",
        "imageURL": "https://ccdn.lezhin.com/v2/comics/4719049832202240/images/tall.webp?updated=1693388120410&width=156 2x",
        "category": "학원"
    },
    {
        "rank": "72",
        "title": "용애담",
        "artist": "치종자, origin chequer comic",
        "imageURL": "https://ccdn.lezhin.com/v2/comics/5033702089621504/images/tall.webp?updated=1694047139559&width=156 2x",
        "category": "BL"
    },
    {
        "rank": "73",
        "title": "용애담",
        "artist": "하리보",
        "imageURL": "https://ccdn.lezhin.com/v2/comics/4668122139459584/images/tall.webp?updated=1714383918801&width=156 2x",
        "category": "BL"
    },
    {
        "rank": "74",
        "title": "용애담",
        "artist": "더므, 뿅, 도해늘",
        "imageURL": "https://ccdn.lezhin.com/v2/comics/6475731902464000/images/tall.webp?updated=1689903423136&width=156 2x",
        "category": "BL"
    },
    {
        "rank": "75",
        "title": "용애담",
        "artist": "영리터, 묵부, 숨나기",
        "imageURL": "https://ccdn.lezhin.com/v2/comics/5716442866843648/images/tall.webp?updated=1663564921127&width=156 2x",
        "category": "BL"
    },
    {
        "rank": "76",
        "title": "용애담",
        "artist": "9도",
        "imageURL": "https://ccdn.lezhin.com/v2/comics/4747180254625792/images/tall.webp?updated=1708507561266&width=156 2x",
        "category": "BL"
    },
    {
        "rank": "77",
        "title": "용애담",
        "artist": "진5",
        "imageURL": null,
        "category": "BL"
    },
    {
        "rank": "78",
        "title": "용애담",
        "artist": "origin chequer comic, Yuanshangbaiyunjian",
        "imageURL": null,
        "category": "BL"
    },
    {
        "rank": "79",
        "title": "용애담",
        "artist": "LibertyHome, Changpei Tech, Lin Qian",
        "imageURL": "https://ccdn.lezhin.com/v2/comics/5223436403933184/images/tall.webp?updated=1701674811769&width=156 2x",
        "category": "BL"
    },
    {
        "rank": "80",
        "title": "용애담",
        "artist": "인디고",
        "imageURL": "https://ccdn.lezhin.com/v2/comics/312/images/tall.webp?updated=1657095700803&width=156 2x",
        "category": "액션"
    },
    {
        "rank": "81",
        "title": "용애담",
        "artist": "폴빠",
        "imageURL": "https://ccdn.lezhin.com/v2/comics/4711695488647168/images/tall.webp?updated=1597740710969&width=156 2x",
        "category": "판타지"
    },
    {
        "rank": "82",
        "title": "용애담",
        "artist": "카놀라 유",
        "imageURL": "https://ccdn.lezhin.com/v2/comics/4755963969798144/images/tall.webp?updated=1609982435763&width=156 2x",
        "category": "로맨스"
    },
    {
        "rank": "83",
        "title": "용애담",
        "artist": "미카",
        "imageURL": "https://ccdn.lezhin.com/v2/comics/4730942531633152/images/tall.webp?updated=1677823735924&width=156 2x",
        "category": "BL"
    },
    {
        "rank": "84",
        "title": "용애담",
        "artist": "에레세모",
        "imageURL": "https://ccdn.lezhin.com/v2/comics/6181022497832960/images/tall.webp?updated=1711096185282&width=156 2x",
        "category": "BL"
    },
    {
        "rank": "85",
        "title": "용애담",
        "artist": "활기",
        "imageURL": "https://ccdn.lezhin.com/v2/comics/5878601020145664/images/tall.webp?updated=1695273785440&width=156 2x",
        "category": "BL"
    },
    {
        "rank": "86",
        "title": "용애담",
        "artist": "김현식",
        "imageURL": "https://ccdn.lezhin.com/v2/comics/5347996077457408/images/tall.webp?updated=1714116463427&width=156 2x",
        "category": "드라마"
    },
    {
        "rank": "87",
        "title": "용애담",
        "artist": "옹방",
        "imageURL": "https://ccdn.lezhin.com/v2/comics/5123961411272704/images/tall.webp?updated=1707895821880&width=156 2x",
        "category": "백합"
    },
    {
        "rank": "88",
        "title": "용애담",
        "artist": "에레혼, 위츠",
        "imageURL": "https://ccdn.lezhin.com/v2/comics/6585948657745920/images/tall.webp?updated=1689301972149&width=156 2x",
        "category": "BL"
    },
    {
        "rank": "89",
        "title": "용애담",
        "artist": "이만세",
        "imageURL": "https://ccdn.lezhin.com/v2/comics/5318548228997120/images/tall.webp?updated=1646641435226&width=156 2x",
        "category": "BL"
    },
    {
        "rank": "90",
        "title": "용애담",
        "artist": "해태, 늑대별, 나민",
        "imageURL": "https://ccdn.lezhin.com/v2/comics/5098885154537472/images/tall.webp?updated=1710834073479&width=156 2x",
        "category": "BL"
    },
    {
        "rank": "91",
        "title": "용애담",
        "artist": "증조할배",
        "imageURL": "https://ccdn.lezhin.com/v2/comics/4524665480740864/images/tall.webp?updated=1692770273125&width=156 2x",
        "category": "일상"
    },
    {
        "rank": "92",
        "title": "용애담",
        "artist": "히가시무라 아키코",
        "imageURL": "https://ccdn.lezhin.com/v2/comics/5661198095024128/images/tall.webp?updated=1662612653841&width=156 2x",
        "category": "드라마"
    },
    {
        "rank": "93",
        "title": "용애담",
        "artist": "윤재호, 카넬",
        "imageURL": "https://ccdn.lezhin.com/v2/comics/277/images/tall.webp?updated=1712112792949&width=156 2x",
        "category": "판타지"
    },
    {
        "rank": "94",
        "title": "용애담",
        "artist": "윤동백, 도몽, 해저500M",
        "imageURL": "https://ccdn.lezhin.com/v2/comics/5447026838667264/images/tall.webp?updated=1705973936257&width=156 2x",
        "category": "BL"
    },
    {
        "rank": "95",
        "title": "용애담",
        "artist": "로등, 뮤토",
        "imageURL": "https://ccdn.lezhin.com/v2/comics/6558149915115520/images/tall.webp?updated=1712897948268&width=156 2x",
        "category": "BL"
    },
    {
        "rank": "96",
        "title": "용애담",
        "artist": "레드렌",
        "imageURL": "https://ccdn.lezhin.com/v2/comics/174/images/tall.webp?updated=1520223405261&width=156 2x",
        "category": "백합"
    },
    {
        "rank": "97",
        "title": "용애담",
        "artist": "이하나",
        "imageURL": "https://ccdn.lezhin.com/v2/comics/6546398410309632/images/tall.webp?updated=1628564814470&width=156 2x",
        "category": "BL"
    },
    {
        "rank": "98",
        "title": "용애담",
        "artist": "비아이",
        "imageURL": "https://ccdn.lezhin.com/v2/comics/18/images/tall.webp?updated=1601537286472&width=156 2x",
        "category": "로맨스"
    },
    {
        "rank": "99",
        "title": "용애담",
        "artist": "제이드",
        "imageURL": "https://ccdn.lezhin.com/v2/comics/5906526225956864/images/tall.webp?updated=1676280024895&width=156 2x",
        "category": "BL"
    },
    {
        "rank": "100",
        "title": "용애담",
        "artist": "미아키 스가루, 타구치 쇼이치",
        "imageURL": "https://ccdn.lezhin.com/v2/comics/5567772715974656/images/tall.webp?updated=1693906714434&width=156 2x",
        "category": "드라마"
    }
]